quiltx/__init__.py
quiltx/cli.py
quiltx/logs.py
quiltx/stack.py
quiltx/tools/__init__.py
quiltx/tools/config.py
quiltx/tools/logs.py
quiltx/tools/stack.py
quiltx-0.1.3.dist-info/METADATA
quiltx-0.1.3.dist-info/WHEEL
quiltx-0.1.3.dist-info/entry_points.txt
quiltx-0.1.3.dist-info/licenses/LICENSE
quiltx-0.1.3.dist-info/RECORD
