Metadata-Version: 2.4
Name: quiltx
Version: 0.1.3
Summary: Unified toolkit for Quilt workflows.
Project-URL: Homepage, https://github.com/ernest/quiltx
Author: Quiltx Contributors
License:                                  Apache License
License-File: LICENSE
Keywords: quiltx,tools
Classifier: License :: OSI Approved :: MIT License
Classifier: Operating System :: OS Independent
Classifier: Programming Language :: Python :: 3
Requires-Python: >=3.9
Requires-Dist: quilt3
Requires-Dist: rich
Provides-Extra: dev
Requires-Dist: black; extra == 'dev'
Requires-Dist: mypy; extra == 'dev'
Requires-Dist: poethepoet; extra == 'dev'
Requires-Dist: pre-commit; extra == 'dev'
Requires-Dist: pytest; extra == 'dev'
